setup.py
WhammyJammer.egg-info/PKG-INFO
WhammyJammer.egg-info/SOURCES.txt
WhammyJammer.egg-info/dependency_links.txt
WhammyJammer.egg-info/top_level.txt
whammyjammer/__init__.py